verilog/7.FSM/Mealy/Sequence detector/0110/0110.v
// Sequence detector for "0110", Moore machine uses both present state and input to determine output logic. 
// It has two flip flops one for present state and one for next state. We use NS ff to update PS at every +ve clk edge.
// In Moore machine the output logic and next state logic both depend on the present state and present inputs.

module seq_detector (x,clk,reset,z);
input x,clk,reset; output reg z;
parameter S0=0, S1=1, S2=2, S3=3;
reg [0:1] PS,NS;

always@(posedge clk or posedge reset)   // Update ps with ns at the +ve edge of clk. If reset is 1 PS is in state 0. Assign present state in clk triggered always block w non blocking statements
 if(reset) PS <= S0;
 else      PS <= NS;

always @ (PS,x)                        // Anytime PS or input x changes update NS and output z. Compute Next state w blocking assignments.
case(PS)
    S0: begin
        NS = x ? S0 : S1;        // if input is 1 stay in state 0, if 1 go to state 1
        z  = 0;
    end
    S1: begin
        NS = x ? S2 : S1;       // if input is 0 stay in state 1, if 1 go to state 2
        z  = 0;
    end
    S2: begin
        NS = x ? S3 : S1;       // if input is 0 go to state 1, if 1 go to state 3
        z  = 0;
    end
    S3: begin
        NS = x ? S0 : S1;       // if input is 0 go to state 1 and give output z as 1 (hence output depends not only on present state but also given input), if 1 go to state 0 with output z as 0
        z  = x ? 0  : 1;
    end
    endcase
endmodule

verilog/7.FSM/Mealy/Sequence detector/0110/test.v
module test_seq;
reg clk, x ,reset; wire z;

seq_detector SEQ(x,clk,reset,z);

initial 
begin
    $dumpfile ("sequence.vcd");$dumpvars (0,test_seq);
    $monitor ($time," x = %b, z = %b",x,z);
    clk = 1'b0; reset = 1'b1;
    #15 reset =1'b0;
end

always #5 clk = ~clk;

initial 
    begin 
        #12 x = 0; #10 x=0; #10 x=1; #10 x=1;
        #10 x=0; #10 x=1; #10 x=1; #10 x=0;
        #10 x=0; #10 x=1; #10 x=1; #10 x=0;
        #10 $finish;
    end
endmodule

verilog/7.FSM/Mealy/Sequence detector/0110/sequence.vcd
$date
	Mon May  8 23:53:57 2023
$end
$version
	Icarus Verilog
$end
$timescale
	1s
$end
$scope module test_seq $end
$var wire 1 ! z $end
$var reg 1 " clk $end
$var reg 1 # reset $end
$var reg 1 $ x $end
$scope module SEQ $end
$var wire 1 " clk $end
$var wire 1 # reset $end
$var wire 1 $ x $end
$var reg 2 % NS [0:1] $end
$var reg 2 & PS [0:1] $end
$var reg 1 ! z $end
$upscope $end
$upscope $end
$enddefinitions $end
#0
$dumpvars
b0 &
b0x %
x$
1#
0"
0!
$end
#5
1"
#10
0"
#12
b1 %
0$
#15
b1 &
1"
0#
#20
0"
#25
1"
#30
0"
#32
b10 %
1$
#35
b11 %
b10 &
1"
#40
0"
#45
b0 %
b11 &
1"
#50
0"
#52
1!
b1 %
0$
#55
0!
b1 &
1"
#60
0"
#62
b10 %
1$
#65
b11 %
b10 &
1"
#70
0"
#75
b0 %
b11 &
1"
#80
0"
#82
1!
b1 %
0$
#85
0!
b1 &
1"
#90
0"
#95
1"
#100
0"
#102
b10 %
1$
#105
b11 %
b10 &
1"
#110
0"
#115
b0 %
b11 &
1"
#120
0"
#122
1!
b1 %
0$
#125
0!
b1 &
1"
