example.v
module example (A,B,C,D,E,F,Y);
input A,B,C,D,E,F;
output Y;
wire t1,t2,t3,Y;

nand #1 G1 (t1,A,B), G4(Y,t1,t2,t3);
and  #2 G2 (t2,C,~B,D);
nor  #1 G3 (t3,E,F);
endmodule

exampletest.v
module testbench;
reg A,B,C,D,E,F; wire Y;
example DUT(A,B,C,D,E,F,Y);
initial 
begin 
    $dumpfile ("example.vcd");
    $dumpvars (0, testbench);
    $monitor ($time,"A=%b,B=%b,C=%b,D=%b,E=%b,F=%b,Y=%b",A,B,C,D,E,F,Y);
    #5 A=1; B=0; C=0; D=1; E=0; F=0;
    #5 A=0; B=0; C=1; D=1; E=0; F=0;
    #5 A=1; C=0;
    #5 F=1;
    #5 $finish;
end
endmodule

example.vcd
$date
	Wed Apr 12 18:51:46 2023
$end
$version
	Icarus Verilog
$end
$timescale
	1s
$end
$scope module testbench $end
$var wire 1 ! Y $end
$var reg 1 " A $end
$var reg 1 # B $end
$var reg 1 $ C $end
$var reg 1 % D $end
$var reg 1 & E $end
$var reg 1 ' F $end
$scope module DUT $end
$var wire 1 " A $end
$var wire 1 # B $end
$var wire 1 $ C $end
$var wire 1 % D $end
$var wire 1 & E $end
$var wire 1 ' F $end
$var wire 1 ! Y $end
$var wire 1 ( t1 $end
$var wire 1 ) t2 $end
$var wire 1 * t3 $end
$upscope $end
$upscope $end
$enddefinitions $end
#0
$dumpvars
x*
x)
x(
x'
x&
x%
x$
x#
x"
x!
$end
#5
0'
0&
1%
0$
0#
1"
#6
1*
1(
#7
0)
#8
1!
#10
1$
0"
#12
1)
#13
0!
#15
0$
1"
#17
0)
#18
1!
#20
1'
#21
0*
