verilog/8.Datapath and control path/Booths (not working)/booth.v
module BOOTH (ldA,ldQ,ldM,clrA,clrQ,clrff,sftA,sftQ,addsub,decr,ldcnt,data_in,clk,qm1,q0,eqz);

input ldA,ldQ,ldM,clrA,clrQ,clrff,sftA,sftQ,addsub,clk,decr,ldcnt;
input [15:0] data_in;
output qm1,q0,eqz;
wire [15:0] A,M,Q,Z;
wire [4:0] count;

assign eqz = ~|count;
assign q0 = Q[0];

shiftreg AR(A,Z,A[15],clk,ldA,clrA,sftA);
shiftreg QR(Q,data_in,A[0],clk,ldQ,clrQ,sftQ);
dff QM1 (Q[0],qm1,clk,clrff);
PIPO MR(data_in,M,clk,ldM);
ALU AS(Z,A,M,addsub);
counter CN(count,decr,ldcnt,clk);

endmodule

module shiftreg(data_out,data_in,s_in,clk,ld,clr,sft);

input s_in, clk, ld, clr, sft;
input [15:0] data_in;
output reg [15:0] data_out;

always @ (posedge clk)
begin
    if(clr) data_out<=0;
    else if (ld) data_out<=data_in;
    else if (sft)
    data_out<= {s_in,data_out[15:1]};
end
endmodule

module PIPO (data_out,data_in,clk,load);

input [15:0] data_in;
input load,clk;
output reg [15:0] data_out;

always @(posedge clk)
 if(load) data_out<= data_in;
endmodule

module dff(d,q,clk,clr);

input d,clk,clr;
output reg q;

always @(posedge clk)
 if(clr) q<=0;
 else q<=d;
endmodule

module ALU (out,in1,in2,addsub);
input [15:0] in1,in2;
input addsub;
output reg[15:0] out;

always@(*)
begin
    if (addsub==0) out = in1-in2;
    else out = in1+in2;
end
endmodule

module counter(data_out,decr,ldcnt,clk);
input decr,clk,ldcnt;
output reg [4:0]  data_out;

always @(posedge clk)
begin
    if(ldcnt) data_out <= 5'b10000;
    else if (decr) data_out<=data_out-1;
end
endmodule

module boothcontroller(ldA,clrA,sftA,ldQ,clrQ,sftQ,ldM,clrff,addsub,start,decr,ldcnt,done,clk,q0,qm1,eqz);

input clk,q0,qm1,start,eqz;
output reg ldA,clrA,sftA,ldQ,clrQ,sftQ,ldM,clrff,addsub,decr,ldcnt,done;

reg [2:0] state;
parameter S0 = 3'b000,S1=3'b001,S2=3'b010,S3=3'b011,S4=3'b100,S5=3'b101,S6=3'b110;

always @(posedge clk)
begin
    case(state)
    S0: if(start) state<=S1;
    S1: state <=S2;
    S2: #2 if({q0,qm1}==2'b01) state <= S3;                            // We give a delay in such statements so as to avoid race condition, if the values of q0 and qm1 by chance happen to change at the +ve edge of clk then the output will wrong.
        else if ({q0,qm1}==2'b10) state<= S4;
        else state <= S5;
    S3: state<=S5;
    S4: state<=S5;
    S5: #2 if({q0,qm1}==2'b01 && !eqz) state <= S3;
        else if ({q0,qm1}==2'b10 && !eqz) state<= S4;
        else if ({q0,qm1}==2'b00 && !eqz) state<= S5;
        else if ({q0,qm1}==2'b11 && !eqz) state<= S5;
        else if (eqz)state <= S6;
    S6: state <= S6;
    default: state<=S0;
    endcase
end

always @(state)
begin
    case(state)
    S0: begin clrA=0; ldA=0; sftA=0;clrQ=0;ldQ=0;sftQ=0;ldM=0;clrff=0;done=0;end
    S1: begin clrA=1; clrff=1; ldcnt=1; ldM=1; end
    S2: begin clrA=0;clrff=0;ldcnt=0;ldM=0;ldQ=1; end
    S3: begin ldA=1;addsub=1;ldQ=0;sftA=0;sftQ=0;decr=0;end
    S4: begin ldA=1;addsub=0;ldQ=0;sftA=0;sftQ=0;decr=0;end
    S5: begin sftA=1;sftQ=1;ldA=0;ldQ=0;decr=1;end
    S6: done=1;
    default: begin clrA=0;sftA=0;ldQ=0;sftQ=0;end
    endcase
end
endmodule

verilog/8.Datapath and control path/Booths (not working)/boothtest.v
module boothtest; 
reg [15:0] data_in;
reg clk, start; 
wire done;


BOOTH DP(ldA,ldQ,ldM,clrA,clrQ,clrff,sftA,sftQ,addsub,decr,ldcnt,data_in,clk,qm1,q0,eqz);
boothcontroller CP  (ldA,clrA,sftA,ldQ,clrQ,sftQ,ldM,clrff,addsub,start,decr,ldcnt,done,clk,q0,qm1,eqz);

initial 
 begin
    clk = 1'b0;
#3  start = 1'b1;
#500 $finish;
 end

always #5 clk = ~clk;

initial 
 begin
    #12 data_in = -32768 ;
    #10 data_in = 32767;
 end

initial 
 begin 
    $monitor ($time, " A=%d  Q=%d  done=%b",DP.A,DP.Q,done);
    $dumpfile ("booth.vcd"); $dumpvars (0,boothtest);
 end
endmodule

verilog/8.Datapath and control path/Booths (not working)/booth.vcd
$date
	Thu May 11 20:05:22 2023
$end
$version
	Icarus Verilog
$end
$timescale
	1s
$end
$scope module boothtest $end
$var wire 1 ! sftQ $end
$var wire 1 " sftA $end
$var wire 1 # qm1 $end
$var wire 1 $ q0 $end
$var wire 1 % ldcnt $end
$var wire 1 & ldQ $end
$var wire 1 ' ldM $end
$var wire 1 ( ldA $end
$var wire 1 ) eqz $end
$var wire 1 * done $end
$var wire 1 + decr $end
$var wire 1 , clrff $end
$var wire 1 - clrQ $end
$var wire 1 . clrA $end
$var wire 1 / addsub $end
$var reg 1 0 clk $end
$var reg 16 1 data_in [15:0] $end
$var reg 1 2 start $end
$scope module CP $end
$var wire 1 0 clk $end
$var wire 1 2 start $end
$var wire 1 # qm1 $end
$var wire 1 $ q0 $end
$var wire 1 ) eqz $end
$var reg 1 / addsub $end
$var reg 1 . clrA $end
$var reg 1 - clrQ $end
$var reg 1 , clrff $end
$var reg 1 + decr $end
$var reg 1 * done $end
$var reg 1 ( ldA $end
$var reg 1 ' ldM $end
$var reg 1 & ldQ $end
$var reg 1 % ldcnt $end
$var reg 1 " sftA $end
$var reg 1 ! sftQ $end
$var reg 3 3 state [2:0] $end
$upscope $end
$scope module DP $end
$var wire 16 4 M [15:0] $end
$var wire 1 / addsub $end
$var wire 1 0 clk $end
$var wire 1 . clrA $end
$var wire 1 - clrQ $end
$var wire 1 , clrff $end
$var wire 16 5 data_in [15:0] $end
$var wire 1 + decr $end
$var wire 1 ( ldA $end
$var wire 1 ' ldM $end
$var wire 1 & ldQ $end
$var wire 1 % ldcnt $end
$var wire 1 " sftA $end
$var wire 1 ! sftQ $end
$var wire 1 # qm1 $end
$var wire 1 $ q0 $end
$var wire 1 ) eqz $end
$var wire 5 6 count [4:0] $end
$var wire 16 7 Z [15:0] $end
$var wire 16 8 Q [15:0] $end
$var wire 16 9 A [15:0] $end
$scope module AR $end
$var wire 1 0 clk $end
$var wire 1 . clr $end
$var wire 1 ( ld $end
$var wire 1 : s_in $end
$var wire 1 " sft $end
$var wire 16 ; data_in [15:0] $end
$var reg 16 < data_out [15:0] $end
$upscope $end
$scope module AS $end
$var wire 1 / addsub $end
$var wire 16 = in1 [15:0] $end
$var wire 16 > in2 [15:0] $end
$var reg 16 ? out [15:0] $end
$upscope $end
$scope module CN $end
$var wire 1 0 clk $end
$var wire 1 + decr $end
$var wire 1 % ldcnt $end
$var reg 5 @ data_out [4:0] $end
$upscope $end
$scope module MR $end
$var wire 1 0 clk $end
$var wire 16 A data_in [15:0] $end
$var wire 1 ' load $end
$var reg 16 B data_out [15:0] $end
$upscope $end
$scope module QM1 $end
$var wire 1 0 clk $end
$var wire 1 , clr $end
$var wire 1 C d $end
$var reg 1 # q $end
$upscope $end
$scope module QR $end
$var wire 1 0 clk $end
$var wire 1 - clr $end
$var wire 16 D data_in [15:0] $end
$var wire 1 & ld $end
$var wire 1 E s_in $end
$var wire 1 ! sft $end
$var reg 16 F data_out [15:0] $end
$upscope $end
$upscope $end
$upscope $end
$enddefinitions $end
#0
$dumpvars
bx F
xE
bx D
xC
bx B
bz A
bx @
bx ?
bz >
bx =
bx <
bx ;
x:
bx 9
bx 8
bx 7
bx 6
bx 5
bz 4
bx 3
x2
bx 1
00
x/
x.
x-
x,
x+
x*
x)
x(
x'
x&
x%
x$
x#
x"
x!
$end
#3
12
#5
0*
0,
0'
0!
0&
0-
0"
0(
0.
b0 3
10
#10
00
#12
b1000000000000000 1
#15
1'
1%
1,
1.
b1 3
10
#20
00
#22
b111111111111111 1
#25
0E
0:
1&
0'
0%
0,
0.
b0 9
b0 <
b0 =
0#
b111111111111111 5
b111111111111111 D
bz B
0)
b10000 6
b10000 @
b10 3
10
#30
00
#35
1C
1$
x#
b111111111111111 8
b111111111111111 F
10
#37
1+
0&
1!
1"
b101 3
#40
00
#45
b11111111111111 8
b11111111111111 F
1#
b1111 6
b1111 @
10
#50
00
#55
b1110 6
b1110 @
b1111111111111 8
b1111111111111 F
10
#60
00
#65
b111111111111 8
b111111111111 F
b1101 6
b1101 @
10
#70
00
#75
b1100 6
b1100 @
b11111111111 8
b11111111111 F
10
#80
00
#85
b1111111111 8
b1111111111 F
b1011 6
b1011 @
10
#90
00
#95
b1010 6
b1010 @
b111111111 8
b111111111 F
10
#100
00
#105
b11111111 8
b11111111 F
b1001 6
b1001 @
10
#110
00
#115
b1000 6
b1000 @
b1111111 8
b1111111 F
10
#120
00
#125
b111111 8
b111111 F
b111 6
b111 @
10
#130
00
#135
b110 6
b110 @
b11111 8
b11111 F
10
#140
00
#145
b1111 8
b1111 F
b101 6
b101 @
10
#150
00
#155
b100 6
b100 @
b111 8
b111 F
10
#160
00
#165
b11 8
b11 F
b11 6
b11 @
10
#170
00
#175
b10 6
b10 @
b1 8
b1 F
10
#180
00
#185
0C
0$
b0 8
b0 F
b1 6
b1 @
10
#187
0+
0!
0"
1/
1(
b11 3
#190
00
#195
xE
x:
1+
0(
1!
1"
0#
bx 9
bx <
bx =
b101 3
10
#200
00
#205
bx000000000000000 8
bx000000000000000 F
1)
b0 6
b0 @
10
#207
1*
b110 3
#210
00
#215
0)
b11111 6
b11111 @
bx00000000000000 8
bx00000000000000 F
10
#220
00
#225
bx0000000000000 8
bx0000000000000 F
b11110 6
b11110 @
10
#230
00
#235
b11101 6
b11101 @
bx000000000000 8
bx000000000000 F
10
#240
00
#245
bx00000000000 8
bx00000000000 F
b11100 6
b11100 @
10
#250
00
#255
b11011 6
b11011 @
bx0000000000 8
bx0000000000 F
10
#260
00
#265
bx000000000 8
bx000000000 F
b11010 6
b11010 @
10
#270
00
#275
b11001 6
b11001 @
bx00000000 8
bx00000000 F
10
#280
00
#285
bx0000000 8
bx0000000 F
b11000 6
b11000 @
10
#290
00
#295
b10111 6
b10111 @
bx000000 8
bx000000 F
10
#300
00
#305
bx00000 8
bx00000 F
b10110 6
b10110 @
10
#310
00
#315
b10101 6
b10101 @
bx0000 8
bx0000 F
10
#320
00
#325
bx000 8
bx000 F
b10100 6
b10100 @
10
#330
00
#335
b10011 6
b10011 @
bx00 8
bx00 F
10
#340
00
#345
bx0 8
bx0 F
b10010 6
b10010 @
10
#350
00
#355
xC
x$
b10001 6
b10001 @
bx 8
bx F
10
#360
00
#365
x#
b10000 6
b10000 @
10
#370
00
#375
b1111 6
b1111 @
10
#380
00
#385
b1110 6
b1110 @
10
#390
00
#395
b1101 6
b1101 @
10
#400
00
#405
b1100 6
b1100 @
10
#410
00
#415
b1011 6
b1011 @
10
#420
00
#425
b1010 6
b1010 @
10
#430
00
#435
b1001 6
b1001 @
10
#440
00
#445
b1000 6
b1000 @
10
#450
00
#455
b111 6
b111 @
10
#460
00
#465
b110 6
b110 @
10
#470
00
#475
b101 6
b101 @
10
#480
00
#485
b100 6
b100 @
10
#490
00
#495
b11 6
b11 @
10
