verilog/8.Datapath and control path/multiply by repeated add/v1/mul.v
// DATAPATH 
module MUL_datapath (eqz,LdA,LdB,LdP,clrp,decB,data_in,clk);
input LdA,LdB,LdP,clrp,clk,decB;
input [15:0] data_in;
output eqz;
wire [15:0] X,Y,Z,Bout,Bus;

assign Bus = data_in;

PIPO1 A (X,Bus,LdA,clk);
PIPO2 P (Y,Z,LdP,clrp,clk);
CNTR  B (Bout,Bus,LdB,decB,clk);
ADD   AD (Z,X,Y);
EQZ COMP(eqz,Bout);
endmodule

module PIPO1 (dout,din,ld,clk);  // parallel in parallel out register without clear
input [15:0] din;
input ld,clk;
output reg[15:0] dout;

always @ (posedge clk)
    if(ld) dout <= din;
endmodule

module PIPO2 (dout,din,ld,clr,clk);      // parallel in parallel out register with clear
input [15:0] din;
input ld,clr,clk;
output reg [15:0] dout;

always @(posedge clk)
if (clr) dout <= 16'b0;
else if(ld) dout <= din;
endmodule

module CNTR (dout,din,ld,dec,clk);      // down counter 
input [15:0] din;
input ld,dec,clk; 
output reg [15:0] dout;

always @ (posedge clk)
 if (ld) dout <= din;
 else if (dec) dout <= dout-1;
endmodule

module ADD (out,in1,in2);
input [15:0] in1,in2; output reg [15:0] out;        

always@(*)
    out = in1 + in2;
endmodule

module EQZ (eqz,data);
input [15:0] data;
output eqz;

assign eqz = (data == 0);
endmodule


// Control Path
module controller (LdA,LdB,LdP,clrp,decB,done,clk,eqz,start);
input clk,eqz,start;
output reg LdA,LdB,LdP,clrp,decB,done;

reg [2:0] state;
parameter S0=3'b000, S1=3'b001, S2=3'b010, S3=3'b011, S4=3'b100;

always @ (posedge clk)          // Assign state with +ve edge clock with non blocking assignments
begin 
    case (state)
    S0: if(start) state <= S1;
    S1: state <= S2;
    S2: state <= S3;
    S3: #2 if(eqz) state <= S4;
    S4: state <= S4;
    default: state <= S0;
    endcase
end

always @ (state)                // Whenever the state changes generate the control signals using blocking assignments based on current state.
    begin
        case(state)
        S0: begin #1 LdA = 0; LdB = 0; LdP = 0; clrp = 0; decB = 0; end    // set all signals to 0
        S1: begin #1 LdA = 1; end                                          // load A
        S2: begin #1 LdA = 0; LdB = 1; clrp = 1; end                       // make ldA to 0.make ldb and clrp 1
        S3: begin #1 LdB = 0; clrp = 0; LdP = 1; decB = 1; end             // make ldB and clrp to 0.make ldp and decb 1
        S4: begin #1 done = 1; LdP = 0; decB = 0; end                      // make ldp and decb to 0. make done to 1
   default: begin #1 LdA = 0; LdB = 0; LdP = 0; clrp = 0; decB = 0; end
        endcase
    end
endmodule


/* Alternate way is t0 assign next state in first always block and then calculate state in the 2nd always block 

module controller (LdA,LdB,LdP,clrp,decB,done,clk,eqz,start);
input clk,eqz,start;
output reg LdA,LdB,LdP,clrp,decB,done;

reg [2:0] state, next_state;
parameter S0=3'b000, S1=3'b001, S2=3'b010, S3=3'b011, S4=3'b100;

always @ (posedge clk)          // Assign state with +ve edge clock with non blocking assignments
begin 
    case (state)
    S0: if(start) state <= S1;
    S1: state <= S2;
    S2: state <= S3;
    S3: #2 if(eqz) state <= S4;
    S4: state <= S4;
    default: state <= S0;
    endcase
end

always @ (state)                // Whenever the state changes generate the control signals using blocking assignments based on current state.
    begin
        case(state)
        S0: begin next_state = S1; #1 LdA = 0; LdB = 0; LdP = 0; clrp = 0; decB = 0;  end    // set all signals to 0
        S1: begin if(start) next_state = S2;#1 LdA = 1; end                                          // load A
        S2: begin #1 LdA = 0; LdB = 1; clrp = 1; end                       // make ldA to 0.make ldb and clrp 1
        S3: begin #1 LdB = 0; clrp = 0; LdP = 1; decB = 1; end             // make ldB and clrp to 0.make ldp and decb 1
        S4: begin #1 done = 1; LdP = 0; decB = 0; end                      // make ldp and decb to 0. make done to 1
   default: begin #1 LdA = 0; LdB = 0; LdP = 0; clrp = 0; decB = 0; end
        endcase
    end
endmodule

*/

verilog/8.Datapath and control path/multiply by repeated add/v2/multest.v
module MUL_test; 
reg [15:0] data_in;
reg clk, start;
wire done; 

MUL_datapath DP (eqz,LdA,LdB,LdP,clrp,decB,data_in,clk);
controller CON (LdA,LdB,LdP,clrp,decB,done,clk,eqz,start);

initial 
begin
    clk = 1'b0;
    #3 start =1'b1;
    #500 $finish;
end

always #5 clk = ~clk;

initial
begin
    #17 data_in = 17;
    #10 data_in = 5;
end
initial 
begin
    $monitor ($time, " in = %b , start = %b, OUT = %d, Done = %b, State = %b",data_in,start,DP.Y,done, CON.state);
    $dumpfile ("mul.vcd"); $dumpvars (0,MUL_test);
end
endmodule

verilog/8.Datapath and control path/multiply by repeated add/v1/mul.vcd
$date
	Wed May 10 00:25:07 2023
$end
$version
	Icarus Verilog
$end
$timescale
	1s
$end
$scope module MUL_test $end
$var wire 1 ! eqz $end
$var wire 1 " done $end
$var wire 1 # decB $end
$var wire 1 $ clrp $end
$var wire 1 % LdP $end
$var wire 1 & LdB $end
$var wire 1 ' LdA $end
$var reg 1 ( clk $end
$var reg 16 ) data_in [15:0] $end
$var reg 1 * start $end
$scope module CON $end
$var wire 1 ( clk $end
$var wire 1 * start $end
$var wire 1 ! eqz $end
$var reg 1 ' LdA $end
$var reg 1 & LdB $end
$var reg 1 % LdP $end
$var reg 1 $ clrp $end
$var reg 1 # decB $end
$var reg 1 " done $end
$var reg 3 + state [2:0] $end
$upscope $end
$scope module DP $end
$var wire 16 , Bus [15:0] $end
$var wire 1 ' LdA $end
$var wire 1 & LdB $end
$var wire 1 % LdP $end
$var wire 1 ( clk $end
$var wire 1 $ clrp $end
$var wire 16 - data_in [15:0] $end
$var wire 1 # decB $end
$var wire 1 ! eqz $end
$var wire 16 . Z [15:0] $end
$var wire 16 / Y [15:0] $end
$var wire 16 0 X [15:0] $end
$var wire 16 1 Bout [15:0] $end
$scope module A $end
$var wire 1 ( clk $end
$var wire 16 2 din [15:0] $end
$var wire 1 ' ld $end
$var reg 16 3 dout [15:0] $end
$upscope $end
$scope module AD $end
$var wire 16 4 in1 [15:0] $end
$var wire 16 5 in2 [15:0] $end
$var reg 16 6 out [15:0] $end
$upscope $end
$scope module B $end
$var wire 1 ( clk $end
$var wire 1 # dec $end
$var wire 16 7 din [15:0] $end
$var wire 1 & ld $end
$var reg 16 8 dout [15:0] $end
$upscope $end
$scope module COMP $end
$var wire 16 9 data [15:0] $end
$var wire 1 ! eqz $end
$upscope $end
$scope module P $end
$var wire 1 ( clk $end
$var wire 1 $ clr $end
$var wire 16 : din [15:0] $end
$var wire 1 % ld $end
$var reg 16 ; dout [15:0] $end
$upscope $end
$upscope $end
$upscope $end
$enddefinitions $end
#0
$dumpvars
bx ;
bx :
bx 9
bx 8
bx 7
bx 6
bx 5
bx 4
bx 3
bx 2
bx 1
bx 0
bx /
bx .
bx -
bx ,
bx +
x*
bx )
0(
x'
x&
x%
x$
x#
x"
x!
$end
#3
1*
#5
b0 +
1(
#6
0#
0$
0%
0&
0'
#10
0(
#15
b1 +
1(
#16
1'
#17
b10001 ,
b10001 2
b10001 7
b10001 )
b10001 -
#20
0(
#25
b10001 0
b10001 3
b10001 4
b10 +
1(
#26
1$
1&
0'
#27
b101 ,
b101 2
b101 7
b101 )
b101 -
#30
0(
#35
b10001 .
b10001 6
b10001 :
b11 +
0!
b101 1
b101 8
b101 9
b0 /
b0 5
b0 ;
1(
#36
1#
1%
0$
0&
#40
0(
#45
b100010 .
b100010 6
b100010 :
b10001 /
b10001 5
b10001 ;
b100 1
b100 8
b100 9
1(
#50
0(
#55
b110011 .
b110011 6
b110011 :
b11 1
b11 8
b11 9
b100010 /
b100010 5
b100010 ;
1(
#60
0(
#65
b1000100 .
b1000100 6
b1000100 :
b110011 /
b110011 5
b110011 ;
b10 1
b10 8
b10 9
1(
#70
0(
#75
b1010101 .
b1010101 6
b1010101 :
b1 1
b1 8
b1 9
b1000100 /
b1000100 5
b1000100 ;
1(
#80
0(
#85
b1100110 .
b1100110 6
b1100110 :
b1010101 /
b1010101 5
b1010101 ;
1!
b0 1
b0 8
b0 9
1(
#87
b100 +
#88
0#
0%
1"
