verilog/11.pipline modeling/Basic/basic.v
// Basic 3 stage pipeline where 
// stage 1 does x1=a+b ,x2 = c-d. with a delay of #4
// stage 2 does x3=x1+x2. with a delay of #4
// stage 3 does f=x3*d. with a delay of #6
// This is a bad way to model a pipline . Because we use only 1 clock at the inter stage registers in pipline which can lead to race condition. To solve this we must use either master slave flip flops or use two phase clock in alternate stages.
module pipe_ex (F,A,B,C,D,clk);
parameter N = 10;

input [N-1:0] A,B,C,D;
input clk;
output [N-1:0] F;
reg [N-1:0] L12_x1, L12_x2, L12_D, L23_x3, L23_D,L34_F;             // we need 6 latches to store the intermediate values. Value D needs to be forwarded to stage 3 because of dependency.

assign F = L34_F;               // assign the wire F with latch output  

always @(posedge clk)           // ** STAGE 1 ** . 
    begin
        L12_x1 <= #4 A+B;       // latch gets value of A+B after #4 delay
        L12_x2 <= #4 C-D;       // latch gets value of C-D after #4 delay
        L12_D <= D;             // latch gets value of D with no delay
    end

always @ (posedge clk)          // ** STAGE 2 **       
    begin
        L23_x3 <= #4 L12_x1 + L12_x2;           // take value from l12_x1 and l12_x2 to compute and store value in l23_x3 with #4 delay
        L23_D  <= L12_D;                        // latch gets value of D with no delay
    end

always @ (posedge clk)                          // ** STAGE 3** 
begin                                           
    L34_F <= #6 L23_x3 * L23_D;                 // take value from l23_x3 and l23_D to compute and store value in l34_F with #6 delay
end

endmodule

verilog/11.pipline modeling/Basic/basictest.v
module pipe1_test; 

parameter N = 10;
wire [N-1:0] F;
reg [N-1:0] A,B,C,D;
reg clk;

pipe_ex DUT (F,A,B,C,D,clk);

initial clk = 0;

always #10 clk = ~clk;              // clock period 20 so 1st input given at #5 then 2nd inputs given at #25. 1st +ve clk comes at #10, 2nd +ve clk comes at #30

initial 
begin
    #5 A=10; B=12; C=6; D=3; // output F = 75
   #20 A=10; B=10; C=5; D=3; // output F = 66
   #20 A=20; B=11; C=1; D=4; // output F = 112
   #20 A=15; B=10; C=8; D=2; // output F = 62 
   #20 A=8; B=15; C=5; D=0; // output F = 0
   #20 A=10; B=10; C=5; D=3; // output F = 66
   #20 A=10; B=10; C=30; D=1; // output F = 49
   #20 A=30; B=1; C=2; D=4; // output F = 166
end

initial
begin
    $dumpfile("pipe1.vcd");
    $dumpvars(0,pipe1_test);
    $monitor ("Time: %2d, F: %2d",$time,F);
    #300 $finish;
end
endmodule

verilog/11.pipline modeling/Basic/pipe1.vcd
$date
	Sat May 13 20:26:16 2023
$end
$version
	Icarus Verilog
$end
$timescale
	1s
$end
$scope module pipe1_test $end
$var wire 10 ! F [9:0] $end
$var reg 10 " A [9:0] $end
$var reg 10 # B [9:0] $end
$var reg 10 $ C [9:0] $end
$var reg 10 % D [9:0] $end
$var reg 1 & clk $end
$scope module DUT $end
$var wire 10 ' A [9:0] $end
$var wire 10 ( B [9:0] $end
$var wire 10 ) C [9:0] $end
$var wire 10 * D [9:0] $end
$var wire 10 + F [9:0] $end
$var wire 1 & clk $end
$var reg 10 , L12_D [9:0] $end
$var reg 10 - L12_x1 [9:0] $end
$var reg 10 . L12_x2 [9:0] $end
$var reg 10 / L23_D [9:0] $end
$var reg 10 0 L23_x3 [9:0] $end
$var reg 10 1 L34_F [9:0] $end
$upscope $end
$upscope $end
$enddefinitions $end
#0
$dumpvars
bx 1
bx 0
bx /
bx .
bx -
bx ,
bx +
bx *
bx )
bx (
bx '
0&
bx %
bx $
bx #
bx "
bx !
$end
#5
b11 %
b11 *
b110 $
b110 )
b1100 #
b1100 (
b1010 "
b1010 '
#10
b11 ,
1&
#14
b11 .
b10110 -
#20
0&
#25
b101 $
b101 )
b1010 #
b1010 (
#30
b11 /
1&
#34
b11001 0
b10 .
b10100 -
#40
0&
#45
b100 %
b100 *
b1 $
b1 )
b1011 #
b1011 (
b10100 "
b10100 '
#50
b100 ,
1&
#54
b1111111101 .
b11111 -
b10110 0
#56
b1001011 !
b1001011 +
b1001011 1
#60
0&
#65
b10 %
b10 *
b1000 $
b1000 )
b1010 #
b1010 (
b1111 "
b1111 '
#70
b100 /
b10 ,
1&
#74
b11100 0
b110 .
b11001 -
#76
b1000010 !
b1000010 +
b1000010 1
#80
0&
#85
b0 %
b0 *
b101 $
b101 )
b1111 #
b1111 (
b1000 "
b1000 '
#90
b0 ,
b10 /
1&
#94
b101 .
b10111 -
b11111 0
#96
b1110000 !
b1110000 +
b1110000 1
#100
0&
#105
b11 %
b11 *
b1010 #
b1010 (
b1010 "
b1010 '
#110
b0 /
b11 ,
1&
#114
b11100 0
b10 .
b10100 -
#116
b111110 !
b111110 +
b111110 1
#120
0&
#125
b1 %
b1 *
b11110 $
b11110 )
#130
b1 ,
b11 /
1&
#134
b11101 .
b10110 0
#136
b0 !
b0 +
b0 1
#140
0&
#145
b100 %
b100 *
b10 $
b10 )
b1 #
b1 (
b11110 "
b11110 '
#150
b1 /
b100 ,
1&
#154
b110001 0
b1111111110 .
b11111 -
#156
b1000010 !
b1000010 +
b1000010 1
#160
0&
#170
b100 /
1&
#174
b11101 0
#176
b110001 !
b110001 +
b110001 1
#180
0&
#190
1&
#196
b1110100 !
b1110100 +
b1110100 1
