verilog/6.Test benches/shiftreg/shiftreg.v
module shiftreg_4bit(clock,clear,A,E);
input clock,clear,A;
output reg E;
reg B,C,D;

always @(posedge clock or negedge clear)
begin 
    if(!clear) 
    begin 
        B<=0; C<=0; D<=0; E<=0;
    end
else
begin
    E<=D;
    D<=C;
    C<=B;
    B<=A;   
end
end
endmodule

verilog/6.Test benches/shiftreg/shiftregtest.v
// Ensure that the input syncs with the clock cycle .

module shifttest;
reg clk,clr,in; wire out;  

shiftreg_4bit sr (.clock(clk),.clear(clr),.A(in),.E(out));

initial 
begin
    clk = 1'b0; #2 clr = 0; #5 clr = 1; 
end

always #5 clk = ~clk;

initial 
begin 
    #2;   // Done to ensure that the input signal is given at #12 so that the input remains stable till the next clock cycle at #15, 
          //like wise the rest of the inputs are at #22 #32 .. etc
repeat(2)
begin #10 in=0; #10 in=0; #10 in=1; #10 in=1; end
end

initial begin
    $dumpfile ("shiftreg.vcd");
    $dumpvars (0,shifttest);
    #200 $finish;
end
endmodule

verilog/6.Test benches/shiftreg/shiftreg.vcd
$date
	Mon May  8 13:46:01 2023
$end
$version
	Icarus Verilog
$end
$timescale
	1s
$end
$scope module shifttest $end
$var wire 1 ! out $end
$var reg 1 " clk $end
$var reg 1 # clr $end
$var reg 1 $ in $end
$scope module sr $end
$var wire 1 $ A $end
$var wire 1 # clear $end
$var wire 1 " clock $end
$var reg 1 % B $end
$var reg 1 & C $end
$var reg 1 ' D $end
$var reg 1 ! E $end
$upscope $end
$upscope $end
$enddefinitions $end
#0
$dumpvars
x'
x&
x%
x$
x#
0"
x!
$end
#2
0!
0'
0&
0%
0#
#5
1"
#7
1#
#10
0"
#12
0$
#15
1"
#20
0"
#25
1"
#30
0"
#32
1$
#35
1%
1"
#40
0"
#45
1&
1"
#50
0"
#52
0$
#55
0%
1'
1"
#60
0"
#65
0&
1!
1"
#70
0"
#72
1$
#75
1%
0'
1"
#80
0"
#85
1&
0!
1"
#90
0"
#95
1'
1"
#100
0"
#105
1!
1"
