verilog/7.FSM/Moore/sequence/unoptimized/parity.v
module parity_gen (x,clk,z);
input x,clk;
output reg z;
reg even_odd;       // The machine state. We will update this with nonblocking statements with the +ve edge of clock in always block and then use it to update the output register in a seperate always block with blocking statements.
parameter EVEN =0, ODD=1 ;

always @(posedge clk) 
    case(even_odd)
     EVEN: begin
        z <= x ? 1 : 0 ;
        even_odd <= x ? ODD : EVEN;
     end
     ODD: begin
        z <= x ? 0 : 1 ;
        even_odd <= x ? EVEN : ODD;
     end
     default: begin 
        z <= 0;
        even_odd <= EVEN;
     end
    endcase
endmodule

verilog/7.FSM/Moore/sequence/unoptimized/paritytest.v
module test_parity;
reg clk,x; wire z;

parity_gen PAR(x,clk,z);

initial 
begin
    $dumpfile ("parity.vcd"); $dumpvars (0,test_parity);
    $monitor ($time," x = %b, z = %b",x,z);
    clk = 1'b0;
end

always #5 clk = ~clk;

initial 
begin
    #2 x = 0; #10 x = 1; #10 x = 1; #10 x = 1; #10 x = 1;
    #10 x = 0; #10 x = 1; #10 x = 1; #10 x = 1; #10 x = 1;
    #10 x = 1; #10 x = 1; #10 x = 0; #10 x = 1; #10 x = 0;
    #50 $finish;
end
endmodule

verilog/7.FSM/Moore/sequence/unoptimized/parity.vcd
$date
	Mon May  8 18:15:17 2023
$end
$version
	Icarus Verilog
$end
$timescale
	1s
$end
$scope module test_parity $end
$var wire 1 ! z $end
$var reg 1 " clk $end
$var reg 1 # x $end
$scope module PAR $end
$var wire 1 " clk $end
$var wire 1 # x $end
$var reg 1 $ even_odd $end
$var reg 1 ! z $end
$upscope $end
$upscope $end
$enddefinitions $end
#0
$dumpvars
x$
x#
0"
x!
$end
#2
0#
#5
0$
0!
1"
#10
0"
#12
1#
#15
1$
1!
1"
#20
0"
#25
0$
0!
1"
#30
0"
#35
1$
1!
1"
#40
0"
#45
0$
0!
1"
#50
0"
#52
0#
#55
1"
#60
0"
#62
1#
#65
1$
1!
1"
#70
0"
#75
0$
0!
1"
#80
0"
#85
1$
1!
1"
#90
0"
#95
0$
0!
1"
#100
0"
#105
1$
1!
1"
#110
0"
#115
0$
0!
1"
#120
0"
#122
0#
#125
1"
#130
0"
#132
1#
#135
1$
1!
1"
#140
0"
#142
0#
