verilog/7.FSM/Moore/lamp/unoptimized/lamp.v
// Moore machine - output depends only on the present state of the machine. 

module cyclic_lamp(clock,light);
input clock;
output reg [0:3] light;          
parameter S0=0, S1=1, S2=2,S3=3;         // easier to refer in case statement
parameter RED=4'b1000, GREEN=4'b0100, YELLOW=4'b0010, BLUE=4'b0001;
reg [0:1] state; // The machine state. if bits are 00 its binary is 0 which is parameter S0, 01 binary 1 which is S1...

always@(posedge clock)
case (state)
    S0: begin
        light <= RED; state <= S1;
    end 
    S1: begin
        light <= GREEN; state <= S2;
    end
    S2: begin
        light <= YELLOW; state <= S3;
    end
    S3: begin
        light <= BLUE; state <= S0;
    end
    default: begin
        light <= RED; state <= S0;
    end
endcase
endmodule

/*  Above design will create 6 Flip flops - 2 for state and 4 for light. The output lines are also being stored in flipflops since we have used nonblocking assignments triggered by clock edge.
Actually we do not need seperate flip flops for the output since the outputs can be directly generated from the state. 
We can do this by making all assignments to light in a seperate 'always' block and using blocking assignment triggered by state change and not by clock. Not by clock because synthesizer will assume we are trying to do something with registers in sync with clock.
This design is in the lamp2 folder

 module cyclic_lamp(clock,light);
input clock;
output reg [0:3] light;          
parameter S0=0, S1=1, S2=2,S3=3;         
parameter RED=4'b1000, GREEN=4'b0100, YELLOW=4'b0010, BLUE=4'b0001;
reg [0:1] state; 

always@(posedge clock)
case (state)
    S0:  state <= S1;
    S1:  state <= S2;
    S2:  state <= S3;
    S3:  state <= S0;
default: state <= S0; 
endcase

always@(state)
case (state)
 S0:light = RED;
 S1:light = GREEN;
 S2:light = YELLOW;
 S3:light = BLUE;
endcase
endmodule

The synthesis tool will generate only 2 flipflops for the first clock triggered always block. 
The second always block will be generating a combinational circuit that takes state as input and light as output

state(s1s0)  light(R G Y B)
S0:00              1 0 0 0 
S1:01              0 1 0 0
S2:10              0 0 1 0
S3:11              0 0 0 1

Logic expression after minimization - R-'s1's0, G-s0, Y- s1, b- s1s0
*/

verilog/7.FSM/Moore/lamp/optimized/lamptest.v
module testlamp;
reg clk; wire [0:3] light;

cyclic_lamp LAMP (clk,light);

always # 5 clk = ~clk;

initial begin
    clk=1'b0;
    #100 $finish;
end

initial begin
    $dumpfile ("lamp.vcd"); $dumpvars (0,testlamp); $monitor($time, " RGYB: %b", light);
end
endmodule

verilog/7.FSM/Moore/lamp/unoptimized/lamp.vcd
$date
	Mon May  8 17:11:01 2023
$end
$version
	Icarus Verilog
$end
$timescale
	1s
$end
$scope module testlamp $end
$var wire 4 ! light [0:3] $end
$var reg 1 " clk $end
$scope module LAMP $end
$var wire 1 " clock $end
$var reg 4 # light [0:3] $end
$var reg 2 $ state [0:1] $end
$upscope $end
$upscope $end
$enddefinitions $end
#0
$dumpvars
bx $
bx #
0"
bx !
$end
#5
b0 $
b1000 !
b1000 #
1"
#10
0"
#15
b1 $
1"
#20
0"
#25
b10 $
b100 !
b100 #
1"
#30
0"
#35
b11 $
b10 !
b10 #
1"
#40
0"
#45
b0 $
b1 !
b1 #
1"
#50
0"
#55
b1 $
b1000 !
b1000 #
1"
#60
0"
#65
b10 $
b100 !
b100 #
1"
#70
0"
#75
b11 $
b10 !
b10 #
1"
#80
0"
#85
b0 $
b1 !
b1 #
1"
#90
0"
#95
b1 $
b1000 !
b1000 #
1"
