verilog/7.FSM/Moore/lamp/optimized/lamp2.v
/*  Here only 2 latches will be generated for the state. 
The synthesis tool will generate only 2 flipflops for the first clock triggered always block. 
The second always block will be generating a combinational circuit that takes state as input and light as output

state(s1s0)  light(R G Y B)
S0:00              1 0 0 0 
S1:01              0 1 0 0
S2:10              0 0 1 0
S3:11              0 0 0 1

Logic expression after minimization - R-'s1's0, G-s0, Y- s1, B- s1s0

*/

module cyclic_lamp(clock,light);
input clock;
output reg [0:3] light;          
parameter S0=0, S1=1, S2=2,S3=3;         
parameter RED=4'b1000, GREEN=4'b0100, YELLOW=4'b0010, BLUE=4'b0001;
reg [0:1] state; 

always@(posedge clock)
case (state)
    S0:  state <= S1;
    S1:  state <= S2;
    S2:  state <= S3;
    S3:  state <= S0;
default: state <= S0; 
endcase

always@(state)
case (state)
 S0:light = RED;
 S1:light = GREEN;
 S2:light = YELLOW;
 S3:light = BLUE;
endcase
endmodule

verilog/7.FSM/Moore/lamp/optimized/lamptest.v
module testlamp;
reg clk; wire [0:3] light;

cyclic_lamp LAMP (clk,light);

always # 5 clk = ~clk;

initial begin
    clk=1'b0;
    #100 $finish;
end

initial begin
    $dumpfile ("lamp.vcd"); $dumpvars (0,testlamp); $monitor($time, " RGYB: %b", light);
end
endmodule

verilog/7.FSM/Moore/lamp/optimized/lamp.vcd
$date
	Mon May  8 17:16:43 2023
$end
$version
	Icarus Verilog
$end
$timescale
	1s
$end
$scope module testlamp $end
$var wire 4 ! light [0:3] $end
$var reg 1 " clk $end
$scope module LAMP $end
$var wire 1 " clock $end
$var reg 4 # light [0:3] $end
$var reg 2 $ state [0:1] $end
$upscope $end
$upscope $end
$enddefinitions $end
#0
$dumpvars
bx $
bx #
0"
bx !
$end
#5
b1000 !
b1000 #
b0 $
1"
#10
0"
#15
b100 !
b100 #
b1 $
1"
#20
0"
#25
b10 !
b10 #
b10 $
1"
#30
0"
#35
b1 !
b1 #
b11 $
1"
#40
0"
#45
b1000 !
b1000 #
b0 $
1"
#50
0"
#55
b100 !
b100 #
b1 $
1"
#60
0"
#65
b10 !
b10 #
b10 $
1"
#70
0"
#75
b1 !
b1 #
b11 $
1"
#80
0"
#85
b1000 !
b1000 #
b0 $
1"
#90
0"
#95
b100 !
b100 #
b1 $
1"
