verilog/11.pipline modeling/2 phase clock 4 stage pipeline/complex.v
// 4 stage pipeline with inputs - 3 register addresses (rs1,rs2,rd), ALU function (func), memory address (addr)
// Stage 1: read two 16 bit numbers from registers specified by rs1 and rs2 and store them in A and B
// Stage 2: Perform an ALU op on A and B specified by func and store in Z.
// Stage 3: write value of Z in reg specified by rd
// Stage 4: also write value of z in mem location 'addr'

module pipeline_ex2(Zout,rs1,rs2,rd,func,addr,clk1,clk2);
input [3:0] rs1,rs2,rd,func; // 4 bit select for 16 16bit registers and 4 bit function for ALU 
input [7:0] addr;            // 8 bit address for 256 memory locations 
input clk1,clk2;             // two phase clock. Used on consecutive stages so as to avoid race condition and ensure stable output at each stage. 
output [15:0] Zout;         //  Output from stage 3 latch L34_Z is assigned to Zout. 

reg [15:0] L12_A, L12_B, L23_Z, L34_Z;  // 16 bit registers to store the intermediate values . Z is forwaded so it can be used in stage 4
reg [3:0] L12_rd, L12_func, L23_rd;     // 4 bit select for register destination which is forwarded till stage 3, ALU function. 
reg [7:0] L12_addr, L23_addr, L34_addr; // 8 bit memory address is forwarded till stage 4.

reg [15:0] regbank [0:15]; // 16 16bit register bank
reg [15:0] mem [0:255];    // 256 16 bit memory locations.

assign Zout = L34_Z;       // Output wire is assigned the output for the 3rd stage latch. 

always @ (posedge clk1)     // ** STAGE 1** 
    begin
        L12_A <= #2 regbank[rs1];          // read A from register bank
        L12_B <= #2 regbank[rs2];          // read B from register bank
       L12_rd <=    rd;                    // forward rd (register write destination)
     L12_addr <=    addr;                  // forward addr (memory write destination)
    end

always @(negedge clk2)      // ** STAGE 2**
    begin
     case (func)
        0: L23_Z <= #2 L12_A + L12_B;   // add
        1: L23_Z <= #2 L12_A - L12_B;   // sub
        2: L23_Z <= #2 L12_A * L12_B;   // mul  
        3: L23_Z <= #2 L12_A;           // select a
        4: L23_Z <= #2 L12_B;           // select b
        5: L23_Z <= #2 L12_A & L12_B;   // and
        6: L23_Z <= #2 L12_A | L12_B;   // or
        7: L23_Z <= #2 L12_A ^ L12_B;   // xor
        8: L23_Z <= #2 ~ L12_A;         // not a
        9: L23_Z <= #2 ~ L12_B;         // not b
       10: L23_Z <= #2 L12_A >> 1;      // right shift
       11: L23_Z <= #2 L12_A << 1;      // left shift
       default: L23_Z <= #2 16'hx;      
     endcase
        L23_rd <= #2 L12_rd;            // forward to stage 3
        L23_addr <= #2 L12_addr;        // forward to stage 3
    end

always @ (posedge clk1)        // ** STAGE 3**
begin
    regbank[L23_rd] <= #2 L23_Z;        // write to register bank from forwaded value 
    L34_addr <= #2 L23_addr;            // forward memory address
    L34_Z <= L23_Z;                     // forward alu output to be written to memory and to be written to output wire Zout
end

always @ (negedge clk2)     // ** STAGE 4 ** 
begin
    mem[L34_addr] <= #2 L34_Z;    // write alu output to location pointed to by the memory address that is forwaded 
end

endmodule

verilog/11.pipline modeling/2 phase clock 4 stage pipeline/complextest.v
module pipe_test;
wire [15:0] Z;
reg [3:0] rs1, rs2 , rd , func;
reg [7:0] addr;
reg clk1, clk2;
integer k;

pipeline_ex2 DUT (Z,rs1,rs2,rd,func,addr,clk1,clk2);

initial
 begin
 clk1 = 0; clk2 = 0; 
 repeat (20)        // Generate 2 phase clock
  begin            
   #5 clk1 = 1; #5 clk1 = 0; #5 clk2 = 1; #5 clk2 = 0;   
  end
 end

initial
for (k=0;k<16;k=k+1)
    DUT.regbank[k] = k;         // initialize registers 

initial begin
    #5 rs1 = 3; rs2 = 5; rd = 10; func = 0; addr = 125;     // ADD
   #20 rs1 = 3; rs2 = 8; rd = 12; func = 2; addr = 126;     // MUL      The 2nd input is given after delay #20 because stage 1 will only trigger at the next +ve edge of clock 1 which is after #20. i.e clock period is 20
   #20 rs1 = 10; rs2 = 5; rd = 14; func = 1; addr = 128;     // SUB     Register 10 has been given a value at #5 that value will be used for computation
   #20 rs1 = 7; rs2 = 3; rd = 13; func = 11; addr = 127;     // SLA
   #20 rs1 = 10; rs2 = 5; rd = 15; func = 1; addr = 129;     // SUB
   #20 rs1 = 12; rs2 = 13; rd = 16; func = 0; addr = 130;     // ADD

   #60 for (k=125;k<131;k=k+1)
        $display ("Mem[%3d] = %3d",k,DUT.mem[k]);
end

initial 
    begin 
        $dumpfile ("pipe2.vcd");
        $dumpvars (0, pipe_test);
        $monitor ("Time: %3d, F = %3d", $time, Z);
        #300 $finish;
    end
endmodule

verilog/11.pipline modeling/2 phase clock 4 stage pipeline/pipe2.vcd
$date
	Sat May 13 23:40:35 2023
$end
$version
	Icarus Verilog
$end
$timescale
	1s
$end
$scope module pipe_test $end
$var wire 16 ! Z [15:0] $end
$var reg 8 " addr [7:0] $end
$var reg 1 # clk1 $end
$var reg 1 $ clk2 $end
$var reg 4 % func [3:0] $end
$var reg 4 & rd [3:0] $end
$var reg 4 ' rs1 [3:0] $end
$var reg 4 ( rs2 [3:0] $end
$var integer 32 ) k [31:0] $end
$scope module DUT $end
$var wire 16 * Zout [15:0] $end
$var wire 8 + addr [7:0] $end
$var wire 1 # clk1 $end
$var wire 1 $ clk2 $end
$var wire 4 , func [3:0] $end
$var wire 4 - rd [3:0] $end
$var wire 4 . rs1 [3:0] $end
$var wire 4 / rs2 [3:0] $end
$var reg 16 0 L12_A [15:0] $end
$var reg 16 1 L12_B [15:0] $end
$var reg 8 2 L12_addr [7:0] $end
$var reg 4 3 L12_rd [3:0] $end
$var reg 16 4 L23_Z [15:0] $end
$var reg 8 5 L23_addr [7:0] $end
$var reg 4 6 L23_rd [3:0] $end
$var reg 16 7 L34_Z [15:0] $end
$var reg 8 8 L34_addr [7:0] $end
$upscope $end
$upscope $end
$enddefinitions $end
#0
$dumpvars
bx 8
bx 7
bx 6
bx 5
bx 4
bx 3
bx 2
bx 1
bx 0
bx /
bx .
bx -
bx ,
bx +
bx *
b10000 )
bx (
bx '
bx &
bx %
0$
0#
bx "
bx !
$end
#5
b1111101 2
b1010 3
b1111101 "
b1111101 +
b0 %
b0 ,
b1010 &
b1010 -
b101 (
b101 /
b11 '
b11 .
1#
#7
b101 1
b11 0
#10
0#
#15
1$
#20
0$
#22
b1111101 5
b1010 6
b1000 4
#25
b1000 !
b1000 *
b1000 7
b1111110 2
b1100 3
1#
b1111110 "
b1111110 +
b10 %
b10 ,
b1100 &
b1100 -
b1000 (
b1000 /
#27
b1111101 8
b1000 1
#30
0#
#35
1$
#40
0$
#42
b1111110 5
b1100 6
b11000 4
#45
b10000000 2
b1110 3
b11000 !
b11000 *
b11000 7
1#
b10000000 "
b10000000 +
b1 %
b1 ,
b1110 &
b1110 -
b101 (
b101 /
b1010 '
b1010 .
#47
b101 1
b1000 0
b1111110 8
#50
0#
#55
1$
#60
0$
#62
b10000000 5
b1110 6
b11 4
#65
b11 !
b11 *
b11 7
b1111111 2
b1101 3
1#
b1111111 "
b1111111 +
b1011 %
b1011 ,
b1101 &
b1101 -
b11 (
b11 /
b111 '
b111 .
#67
b10000000 8
b11 1
b111 0
#70
0#
#75
1$
#80
0$
#82
b1111111 5
b1101 6
b1110 4
#85
b10000001 2
b1111 3
b1110 !
b1110 *
b1110 7
1#
b10000001 "
b10000001 +
b1 %
b1 ,
b1111 &
b1111 -
b101 (
b101 /
b1010 '
b1010 .
#87
b101 1
b1000 0
b1111111 8
#90
0#
#95
1$
#100
0$
#102
b10000001 5
b1111 6
b11 4
#105
b11 !
b11 *
b11 7
b10000010 2
b0 3
1#
b10000010 "
b10000010 +
b0 %
b0 ,
b0 &
b0 -
b1101 (
b1101 /
b1100 '
b1100 .
#107
b10000001 8
b1110 1
b11000 0
#110
0#
#115
1$
#120
0$
#122
b10000010 5
b0 6
b100110 4
#125
b100110 !
b100110 *
b100110 7
1#
#127
b10000010 8
#130
0#
#135
1$
#140
0$
#145
1#
#150
0#
#155
1$
#160
0$
#165
1#
b10000011 )
